event_model/__init__.py
event_model/__main__.py
event_model/_version.py
event_model/py.typed
event_model/basemodels/__init__.py
event_model/basemodels/datum.py
event_model/basemodels/datum_page.py
event_model/basemodels/event.py
event_model/basemodels/event_descriptor.py
event_model/basemodels/event_page.py
event_model/basemodels/resource.py
event_model/basemodels/run_start.py
event_model/basemodels/run_stop.py
event_model/basemodels/stream_datum.py
event_model/basemodels/stream_resource.py
event_model/documents/__init__.py
event_model/documents/datum.py
event_model/documents/datum_page.py
event_model/documents/event.py
event_model/documents/event_descriptor.py
event_model/documents/event_page.py
event_model/documents/resource.py
event_model/documents/run_start.py
event_model/documents/run_stop.py
event_model/documents/stream_datum.py
event_model/documents/stream_resource.py
event_model/generate/__init__.py
event_model/generate/__main__.py
event_model/generate/create_documents.py
event_model/generate/templates/root.jinja2
event_model/schemas/bulk_datum.json
event_model/schemas/bulk_events.json
event_model/schemas/datum.json
event_model/schemas/datum_page.json
event_model/schemas/event.json
event_model/schemas/event_descriptor.json
event_model/schemas/event_page.json
event_model/schemas/resource.json
event_model/schemas/run_start.json
event_model/schemas/run_stop.json
event_model/schemas/stream_datum.json
event_model/schemas/stream_resource.json
event_model/tests/__init__.py
event_model/tests/test_auth.py
event_model/tests/test_em.py
event_model/tests/test_emit.py
event_model/tests/test_filler.py
event_model/tests/test_projections.py
event_model/tests/test_run_router.py
event_model/tests/test_schema_generation.py
event_model-1.23.1.dist-info/licenses/LICENSE
event_model-1.23.1.dist-info/METADATA
event_model-1.23.1.dist-info/WHEEL
event_model-1.23.1.dist-info/top_level.txt
event_model-1.23.1.dist-info/RECORD
