Metadata-Version: 2.4
Name: event-model
Version: 1.23.1
Summary: Data model used by the bluesky ecosystem.
Author-email: Brookhaven National Lab <dallan@bnl.gov>
License: BSD 3-Clause License
Project-URL: GitHub, https://github.com/bluesky/event-model
Classifier: Development Status :: 3 - Alpha
Classifier: License :: OSI Approved :: BSD License
Classifier: Programming Language :: Python :: 3.8
Classifier: Programming Language :: Python :: 3.9
Classifier: Programming Language :: Python :: 3.10
Classifier: Programming Language :: Python :: 3.11
Classifier: Programming Language :: Python :: 3.12
Requires-Python: >=3.8
License-File: LICENSE
Requires-Dist: importlib-resources
Requires-Dist: jsonschema>=4
Requires-Dist: numpy
Requires-Dist: typing_extensions
Provides-Extra: dev
Requires-Dist: mypy; extra == "dev"
Requires-Dist: myst-parser; extra == "dev"
Requires-Dist: pipdeptree; extra == "dev"
Requires-Dist: pre-commit; extra == "dev"
Requires-Dist: pydata-sphinx-theme>=0.12; extra == "dev"
Requires-Dist: pytest; extra == "dev"
Requires-Dist: pytest-cov; extra == "dev"
Requires-Dist: ruff; extra == "dev"
Requires-Dist: sphinx-autobuild; extra == "dev"
Requires-Dist: sphinx-copybutton; extra == "dev"
Requires-Dist: sphinx-design; extra == "dev"
Requires-Dist: tox-direct; extra == "dev"
Requires-Dist: types-mock; extra == "dev"
Requires-Dist: copier; extra == "dev"
Requires-Dist: ipython; extra == "dev"
Requires-Dist: matplotlib; extra == "dev"
Requires-Dist: numpydoc; extra == "dev"
Requires-Dist: pydantic<2.11; extra == "dev"
Requires-Dist: datamodel-code-generator; extra == "dev"
Dynamic: license-file
